specsheet/__init__.py
specsheet/_version.py
specsheet/command.py
specsheet-0.1.0.dist-info/LICENSE
specsheet-0.1.0.dist-info/METADATA
specsheet-0.1.0.dist-info/WHEEL
specsheet-0.1.0.dist-info/entry_points.txt
specsheet-0.1.0.dist-info/top_level.txt
specsheet-0.1.0.dist-info/RECORD
